imagecleaner/__init__.py
imagecleaner/_version.py
imagecleaner/cli.py
imagecleaner-0.4.4.dist-info/METADATA
imagecleaner-0.4.4.dist-info/RECORD
imagecleaner-0.4.4.dist-info/WHEEL
imagecleaner-0.4.4.dist-info/entry_points.txt
imagecleaner-0.4.4.dist-info/top_level.txt
