Metadata-Version: 2.1
Name: imagecleaner
Version: 0.4.4
Summary: Remove duplicated images from a path
Home-page: https://github.com/Kjwon15/image-cleaner
Author: Kjwon15
Author-email: kjwonmail@gmail.com
License: UNKNOWN
Download-URL: https://github.com/Kjwon15/image-cleaner/releases
Platform: UNKNOWN
Requires-Dist: Pillow (>=2.6.1)
Requires-Dist: appdirs (>=1.4.0)
